vizblend/__init__.py
vizblend/create_ppt_report.py
vizblend/create_report.py
vizblend/figure_defaults.py
vizblend-2.0.0.dist-info/LICENSE
vizblend-2.0.0.dist-info/METADATA
vizblend-2.0.0.dist-info/WHEEL
vizblend-2.0.0.dist-info/top_level.txt
vizblend-2.0.0.dist-info/RECORD
