Metadata-Version: 2.2
Name: vizblend
Version: 2.0.0
Summary: Generate multi-page HTML file for Interactive analytical reporting with Python and Plotly
Home-page: https://github.com/MahmoudHousam/VizBlend
Author: Mahmoud Housam
Author-email: mahmoudhousam60@gmail.com
Classifier: Programming Language :: Python :: 3.9
Classifier: Operating System :: OS Independent
Classifier: Development Status :: 4 - Beta
Classifier: License :: OSI Approved :: MIT License
Classifier: Intended Audience :: Developers
Classifier: Topic :: Scientific/Engineering :: Visualization
Requires-Python: >=3.9
License-File: LICENSE
Requires-Dist: plotly==5.24.1
Requires-Dist: black==24.10.0
Requires-Dist: pytest==6.2.4
Requires-Dist: pandas==2.2.3
Requires-Dist: jinja2==3.1.4
Requires-Dist: bs4==0.0.2
Requires-Dist: python-pptx==1.0.2
Requires-Dist: kaleido
Dynamic: author
Dynamic: author-email
Dynamic: classifier
Dynamic: description
Dynamic: description-content-type
Dynamic: home-page
Dynamic: requires-dist
Dynamic: requires-python
Dynamic: summary
